shadowserver/__init__.py
shadowserver/main.py
shadowserver-0.2.4.dist-info/LICENSE
shadowserver-0.2.4.dist-info/METADATA
shadowserver-0.2.4.dist-info/WHEEL
shadowserver-0.2.4.dist-info/top_level.txt
shadowserver-0.2.4.dist-info/RECORD
