Metadata-Version: 2.1
Name: shadowserver
Version: 0.2.4
Summary: An asynchronous HTTP proxy server library using aiohttp, designed to forward requests from clients to a target server
Home-page: https://github.com/benkimz/shadowserver
Author: benkimz
Author-email: benkim3619@gmail.com
Maintainer: benkimz
Maintainer-email: benkim3619@gmail.com
License: MIT
Keywords: proxy,server,proxy-server,http,https,aiohttp,asyncio
Platform: any
Classifier: Programming Language :: Python :: 3
Classifier: License :: OSI Approved :: MIT License
Classifier: Operating System :: OS Independent
License-File: LICENSE
Requires-Dist: aiohttp
Requires-Dist: multidict
Requires-Dist: asyncio
Requires-Dist: Brotli
